sparki_learning/__init__.py
sparki_learning/constants.py
sparki_learning/gui.py
sparki_learning/sparki_myro.py
sparki_learning/speak.py
sparki_learning/sync_lib.py
sparki_learning/util.py
sparki_learning-1.6.9.dist-info/LICENSE
sparki_learning-1.6.9.dist-info/METADATA
sparki_learning-1.6.9.dist-info/WHEEL
sparki_learning-1.6.9.dist-info/top_level.txt
sparki_learning-1.6.9.dist-info/zip-safe
sparki_learning-1.6.9.dist-info/RECORD
