Metadata-Version: 2.1
Name: sparki-learning
Version: 1.6.9
Summary: library to implement the Myro API with the Sparki robot
Home-page: https://github.com/radarjd/sparki_learning
Author: Jeremy Eglen
Author-email: jeglen@butler.edu
License: Apache License Version 2.0
Project-URL: Documentation, https://sparki-learning.readthedocs.io/en/latest/
Project-URL: Source, https://github.com/radarjd/sparki_learning/
Keywords: sparki learning myro robot
Platform: UNKNOWN
Classifier: Development Status :: 5 - Production/Stable
Classifier: Intended Audience :: Education
Classifier: License :: OSI Approved :: Apache Software License
Classifier: Programming Language :: Python
Classifier: Topic :: Education
Classifier: Topic :: Software Development :: Libraries :: Python Modules
Requires-Python: >=3.0, <4
Requires-Dist: pyserial (>=2.7)
Requires-Dist: pysimplegui (>=4.0.0)
